processador/ACControl.v
module accontrol( //Main ULA input accumulator control unit
    jump,
    jumpC,
    sin,
    InA,
    twone,
    saidaMux,
    saidaAc,
);

input jump, jumpC, sin, InA, twone;
output wire saidaMux, saidaAc;
reg saidaM, saidaA;

always @(*)
    begin
        saidaM = twone & ~InA;
        saidaA = ~(jump | jumpC) & (sin | twone);
    end
    assign saidaMux = saidaM;
    assign saidaAc = saidaA;
endmodule

test/ACControl_tb.v
`timescale 1ns/1ns
`include "processador/ACControl.v"


module ACControl_tb;
    reg jump, jumpC, sin, InA, twone;
    wire saidaMux, saidaAc;

    accontrol control (
        .jump(jump),
        .jumpC(jumpC),
        .sin(sin),
        .InA(InA),
        .twone(twone),
        .saidaMux(saidaMux),
        .saidaAc(saidaAc)
    );

    initial begin
        //$monitor("J = %b, Jc = %b, Sin = %b, InA = %b, 1&2 = %b, Mux = %b, AC = %b", jump,jumpC,sin,InA,twone,saidaMux,saidaAc);
        $dumpfile ("testbench/ACControl.vcd");    
	    $dumpvars(0, ACControl_tb);

        jump = 0;
        jumpC = 0;
        sin = 0;
        InA = 0;
        twone = 0;

        #20
        jump = 1;
        jumpC = 0;
        sin = 0;
        InA = 0;
        twone = 0;

        #20
        jump = 0;
        jumpC = 1;
        sin = 0;
        InA = 0;
        twone = 0;

        #20
        jump = 1;
        jumpC = 1;
        sin = 0;
        InA = 0;
        twone = 0;

        #20
        jump = 0;
        jumpC = 0;
        sin = 1;
        InA = 0;
        twone = 0;

        #20
        jump = 0;
        jumpC = 0;
        sin = 1;
        InA = 0;
        twone = 1;

        #20
        jump = 0;
        jumpC = 0;
        sin = 0;
        InA = 0;
        twone = 1;

        #20
        jump = 0;
        jumpC = 0;
        sin = 0;
        InA = 1;
        twone = 1;

        #20
        jump = 0;
        jumpC = 0;
        sin = 0;
        InA = 1;
        twone = 0;

        //$monitor("test completed");
        $display("test completed");
    end

endmodule

testbench/ACControl.vcd
$date
	Sun Sep 27 15:31:23 2020
$end
$version
	Icarus Verilog
$end
$timescale
	1ns
$end
$scope module ACControl_tb $end
$var wire 1 ! saidaMux $end
$var wire 1 " saidaAc $end
$var reg 1 # InA $end
$var reg 1 $ jump $end
$var reg 1 % jumpC $end
$var reg 1 & sin $end
$var reg 1 ' twone $end
$scope module control $end
$var wire 1 # InA $end
$var wire 1 $ jump $end
$var wire 1 % jumpC $end
$var wire 1 " saidaAc $end
$var wire 1 ! saidaMux $end
$var wire 1 & sin $end
$var wire 1 ' twone $end
$var reg 1 ( saidaA $end
$var reg 1 ) saidaM $end
$upscope $end
$upscope $end
$enddefinitions $end
#0
$dumpvars
0)
0(
0'
0&
0%
0$
0#
0"
0!
$end
#20
1$
#40
1%
0$
#60
1$
#80
1"
1(
1&
0%
0$
#100
1!
1)
1'
#120
0&
#140
0!
0)
1#
#160
0"
0(
0'
